djangofoundry/__init__.py
djangofoundry/urls.py
djangofoundry/controllers/__init__.py
djangofoundry/controllers/detail.py
djangofoundry/controllers/generic.py
djangofoundry/controllers/list.py
djangofoundry/controllers/memory.py
djangofoundry/controllers/responses.py
djangofoundry/decorators/__init__.py
djangofoundry/decorators/queryset_filter.py
djangofoundry/decorators/retry.py
djangofoundry/decorators/timeout.py
djangofoundry/exceptions/__init__.py
djangofoundry/exceptions/app.py
djangofoundry/files/.pre-commit-config.yml
djangofoundry/files/package.json
djangofoundry/files/pyproject.toml
djangofoundry/files/urls.py
djangofoundry/files/.github/.workflows/ci.yml
djangofoundry/files/dashboard/urls.py
djangofoundry/files/dashboard/controllers/__init__.py
djangofoundry/files/dashboard/controllers/home.py
djangofoundry/files/dashboard/frontend/sass/style.scss
djangofoundry/files/dashboard/models/__init__.py
djangofoundry/files/dashboard/models/abstract/__init__.py
djangofoundry/files/dashboard/models/abstract/model.py
djangofoundry/files/dashboard/models/abstract/queryset.py
djangofoundry/files/dashboard/templates/dashboard/base.html
djangofoundry/files/dashboard/templates/dashboard/homepage.html
djangofoundry/files/dashboard/templates/dashboard/classes/collapsible_pane.html
djangofoundry/files/dashboard/templates/dashboard/classes/default.html
djangofoundry/files/dashboard/templates/dashboard/classes/loading.html
djangofoundry/files/dashboard/templates/dashboard/classes/pane.html
djangofoundry/files/dashboard/templates/dashboard/classes/tabs.html
djangofoundry/files/dashboard/templates/dashboard/classes/wide.html
djangofoundry/files/dashboard/templates/dashboard/partials/footer.html
djangofoundry/files/dashboard/templates/dashboard/partials/header.html
djangofoundry/files/dashboard/tests/__init__.py
djangofoundry/files/lib/__init__.py
djangofoundry/files/lib/exceptions/__init__.py
djangofoundry/files/lib/exceptions/exceptions.py
djangofoundry-0.0.10.dist-info/METADATA
djangofoundry-0.0.10.dist-info/WHEEL
djangofoundry-0.0.10.dist-info/entry_points.txt
djangofoundry-0.0.10.dist-info/licenses/LICENSE.md
djangofoundry-0.0.10.dist-info/RECORD
