Metadata-Version: 2.4
Name: djangofoundry
Version: 0.0.10
Summary: A collection of classes built on Django to make it easier to build web applications.
Project-URL: Homepage, https://github.com/avranu/djangofoundry
Project-URL: Bug Tracker, https://github.com/avranu/djangofoundry/issues
Author-email: Jess Mann <jess.a.mann+df@gmail.com>
License-File: LICENSE.md
Classifier: License :: OSI Approved :: BSD License
Classifier: Operating System :: OS Independent
Classifier: Programming Language :: Python :: 3
Requires-Python: >=3.12
Requires-Dist: django-auto-prefetch>=1.12.0
Requires-Dist: django-dirtyfields>=1.9.6
Requires-Dist: django-filter>=25.1
Requires-Dist: django-pandas>=0.6.7
Requires-Dist: django-picklefield>=3.3
Requires-Dist: django-postgres-extra>=2.0.4
Requires-Dist: django>=5.1.7
Requires-Dist: jinja2>=3.1.6
Requires-Dist: model-bakery>=1.20.4
Requires-Dist: pandas>=2.2.3
Requires-Dist: psutil>=7.0.0
Requires-Dist: python-dateutil>=2.9.0.post0
Requires-Dist: python-levenshtein>=0.27.1
Requires-Dist: pyyaml>=6.0.2
Requires-Dist: requests>=2.32.3
Requires-Dist: setuptools>=76.1.0
Requires-Dist: thefuzz>=0.22.1
Requires-Dist: toml>=0.10.2
Requires-Dist: typing-extensions>=4.12.2
